litestats/__init__.py
litestats/__main__.py
litestats/litestats.py
litestats/version.py
litestats-1.1.0.dist-info/LICENSE
litestats-1.1.0.dist-info/METADATA
litestats-1.1.0.dist-info/WHEEL
litestats-1.1.0.dist-info/entry_points.txt
litestats-1.1.0.dist-info/top_level.txt
litestats-1.1.0.dist-info/RECORD
