Metadata-Version: 2.1
Name: litestats
Version: 1.1.0
Summary: Convert cprofile/pstats files into sqlite databases.
Home-page: https://github.com/venthur/litestats
Author: Bastian Venthur
Author-email: mail@venthur.de
License: MIT
Project-URL: Source, https://github.com/venthur/litestats
Project-URL: Changelog, https://github.com/venthur/litestats/blob/master/CHANGELOG.md
Keywords: litestats pstats cprofile
Platform: UNKNOWN
Classifier: Development Status :: 5 - Production/Stable
Classifier: Intended Audience :: Developers
Classifier: License :: OSI Approved :: MIT License
Classifier: Programming Language :: Python :: 3
Requires-Python: >=3.6
